setup.cfg
setup.py
jpio/__init__.py
jpio/jstql.py
jpio/run_time.py
jpio.egg-info/PKG-INFO
jpio.egg-info/SOURCES.txt
jpio.egg-info/dependency_links.txt
jpio.egg-info/entry_points.txt
jpio.egg-info/top_level.txt
jpio/extensions/__init__.py
jpio/extensions/default.py
tests/__init__.py
tests/test_functions.py
tests/test_parser.py
tests/test_runtime.py