Metadata-Version: 1.1
Name: jpio
Version: 0.2.0
Summary: Json Python I/O
Home-page: https://github.com/zwodahs/jpio
Author: Eric Ng
Author-email: ericnjf@gmail.com
License: UNKNOWN
Keywords: json,commandline
Platform: UNKNOWN
Classifier: Development Status :: 4 - Beta
Classifier: Environment :: Console
Classifier: Programming Language :: Python :: 3 :: Only
